djikmz/__init__.py
djikmz/task_builder.py
djikmz/model/__init__.py
djikmz/model/action_group.py
djikmz/model/coordinate_system_param.py
djikmz/model/heading_param.py
djikmz/model/kml.py
djikmz/model/mission_config.py
djikmz/model/turn_param.py
djikmz/model/utils.py
djikmz/model/waypoint.py
djikmz/model/action/__init__.py
djikmz/model/action/action.py
djikmz/model/action/camera_actions.py
djikmz/model/action/gimbal_actions.py
djikmz/model/action/movement_actions.py
djikmz/model/action/record_actions.py
djikmz/model/action/registry.py
djikmz-0.1.0.dist-info/licenses/LICENSE
djikmz-0.1.0.dist-info/METADATA
djikmz-0.1.0.dist-info/WHEEL
djikmz-0.1.0.dist-info/top_level.txt
djikmz-0.1.0.dist-info/RECORD
