Metadata-Version: 2.4
Name: djikmz
Version: 0.1.0
Summary: A Python package for generating DJI task plan KMZ files with type safety and integrity checks
Author-email: Zeyu Zhang <andrew.zh@live.com>
License: MIT
Project-URL: Homepage, https://github.com/zhzyx/djikmz
Project-URL: Repository, https://github.com/zhzyx/djikmz
Project-URL: Issues, https://github.com/zhzyx/djikmz/issues
Keywords: dji,kmz,drone,task-plan,waypoint,kml
Classifier: Development Status :: 3 - Alpha
Classifier: Intended Audience :: Developers
Classifier: License :: OSI Approved :: MIT License
Classifier: Topic :: Scientific/Engineering :: GIS
Classifier: Topic :: Software Development :: Libraries :: Python Modules
Requires-Python: >=3.10
License-File: LICENSE
Requires-Dist: pydantic>=2.0.0
Requires-Dist: typing-extensions>=4.0.0
Requires-Dist: xmltodict>=0.14
Provides-Extra: dev
Requires-Dist: pytest>=7.0.0; extra == "dev"
Requires-Dist: pytest-cov>=4.0.0; extra == "dev"
Requires-Dist: black>=23.0.0; extra == "dev"
Requires-Dist: isort>=5.12.0; extra == "dev"
Requires-Dist: mypy>=1.0.0; extra == "dev"
Requires-Dist: flake8>=6.0.0; extra == "dev"
Dynamic: license-file
